{"api_4.12.0.md":"BvphYR1G","api_4.12.1.md":"1D1YWABM","api_4.13.0.md":"DoOkbrfp","api_4.13.1.md":"DGtIaIAO","api_4.13.3.md":"_9fCzotB","api_4.13.5.md":"kIZDR54o","api_4.14.13.md":"B00iT2XG","api_4.14.16.md":"Cd93zo4b","api_4.14.20.md":"Dp0DOZ1e","api_4.14.3.md":"TmCM1WIf","api_4.14.4.md":"C5bvrCn3","api_4.14.6.md":"CAjmD27N","api_4.14.8.md":"DXl2t1L3","api_4.15.1.md":"rYCFLoP4","api_4.15.12.md":"BGzkHVwX","api_4.15.13.md":"BkDW0HA2","api_4.15.17.md":"BRzxKf5G","api_4.15.18.md":"nldXxrJv","api_4.15.19.md":"DUyNyquT","api_4.15.3.md":"DItoyI6E","api_4.15.5.md":"DM8C3Mt6","api_4.15.6.md":"BUqd6Hd9","api_4.15.8.md":"CtPfI7Jl","api_4.16.0.md":"GZzxoP38","api_4.17.0.md":"ByXOt1Zq","api_4.17.1.md":"DNr5Tux3","api_4.17.10.md":"Dm--mA7x","api_4.17.11.md":"ChNXSCzQ","api_4.17.15.md":"uNci92pG","api_4.17.16.md":"D8LefOmo","api_4.17.17.md":"eBYnQmmr","api_4.17.18.md":"QRVrT4lw","api_4.17.2.md":"CdMAxEge","api_4.17.4.md":"Dyl5PVLe","api_4.17.5.md":"CSBHcMek","api_4.17.8.md":"B53s_8JV","api_index.md":"CHrCobsV","config_advanced.md":"Cu9SkMrn","config_basic.md":"BOAAriO9","config_starter.shell.md":"CgykPV8t","develop_api.md":"CvFH7GkQ","develop_api_doc.md":"BRzRJqu4","develop_api_type.md":"Cnlcetfj","develop_event.md":"Dt7t4F2G","develop_file.md":"Db_ccLOp","develop_http-sse.md":"BqL3POfR","develop_msg.md":"_3tJ1HRE","develop_plugin_advanced.md":"BtDVU2qK","develop_plugin_api_doc.md":"C-cH9sfx","develop_plugin_api_type.md":"XCKJBdc1","develop_plugin_hot-reload.md":"BJY7ITeO","develop_plugin_index.md":"D7XvhsnR","develop_plugin_mechanism.md":"Cm7yoGNa","develop_plugin_publish.md":"CfKzNjku","develop_plugin_start-webui.md":"DjmJpjbx","develop_plugin_structure.md":"BMFXpScS","develop_secrity.md":"CySb2wM1","guide_bench-mark.md":"C6ugAOY5","guide_boot_framework.md":"7xjXTO74","guide_boot_linux_startup.md":"UpvXJoQA","guide_boot_release.md":"DsW7fZAW","guide_boot_shell-linux-semiauto.md":"DdMpYRHJ","guide_boot_shell.md":"BTmBbMJN","guide_install.md":"C4cOr-U0","guide_napcat.md":"BxQ0CO9h","guide_start-install.md":"X6oUGumn","index.md":"CF6uM5an","onebot_api.md":"DNqnvzEp","onebot_basic_event.md":"CpWrsFLV","onebot_event.md":"Gii2NsOu","onebot_index.md":"B8aw4qFY","onebot_napcat.md":"B9Gq17Jn","onebot_network.md":"ChRhv87T","onebot_sement.md":"BQyNw_3q","other_about-copy.md":"DKFRPz_4","other_about.md":"C66CLLJC","other_napcat.md":"gdQGi3Cu","other_ntrecall.md":"DwyRr5or","other_security.md":"CFlC2Uth","use_community.md":"BQoWr_bI","use_integration.md":"B1yDZLkT"}
